{
  "title": "Bramhatal Trek",
  "description": "A winter trek to the frozen Bramhatal lake in the Garhwal Himalayas — rhododendron forests, knee-deep snow, and Mt Trishul looming overhead.",
  "date": "2025-01-15",
  "coverImage": "/photos/bramhatal/IMG_0247-scaled.jpg",
  "coverAlt": "Snow-covered trail through rhododendron forest on the way to Bramhatal lake",
  "location": "Uttarakhand, India",
  "images": [
    {
      "src": "/photos/bramhatal/IMG_0247-scaled.jpg",
      "alt": "Trail through rhododendron forest on Day 1 from Lohajung",
      "width": 4032,
      "height": 3024,
      "caption": "Day 1 — Lohajung to Bekaltal"
    },
    {
      "src": "/photos/bramhatal/IMG_0249-scaled.jpg",
      "alt": "Valley views through the forest canopy",
      "width": 4032,
      "height": 3024
    },
    {
      "src": "/photos/bramhatal/IMG_0262-scaled.jpg",
      "alt": "Sunlight filtering through the rhododendron trees",
      "width": 4032,
      "height": 3024
    },
    {
      "src": "/photos/bramhatal/IMG_0288-scaled.jpg",
      "alt": "First glimpses of Himalayan peaks above the treeline",
      "width": 4032,
      "height": 3024
    },
    {
      "src": "/photos/bramhatal/IMG_0293-scaled.jpg",
      "alt": "Approach to Bekaltal campsite",
      "width": 4032,
      "height": 3024
    },
    {
      "src": "/photos/bramhatal/IMG_0316-scaled.jpg",
      "alt": "Snow on the trail as altitude increases",
      "width": 4032,
      "height": 3024
    },
    {
      "src": "/photos/bramhatal/IMG_0321-scaled.jpg",
      "alt": "Morning light on the snow-dusted forest",
      "width": 4032,
      "height": 3024
    },
    {
      "src": "/photos/bramhatal/IMG_0374-scaled.jpg",
      "alt": "Climbing higher on Day 2 toward Bramhatal base",
      "width": 4032,
      "height": 3024,
      "caption": "Day 2 — Bekaltal to Bramhatal Base"
    },
    {
      "src": "/photos/bramhatal/IMG_0377-scaled.jpg",
      "alt": "Trail winding through deep snow",
      "width": 4032,
      "height": 3024
    },
    {
      "src": "/photos/bramhatal/IMG_0409-scaled.jpg",
      "alt": "Panoramic view of the Garhwal Himalayas",
      "width": 4032,
      "height": 3024
    },
    {
      "src": "/photos/bramhatal/IMG_0412-scaled.jpg",
      "alt": "Mt Trishul massif appearing through a break in the trees",
      "width": 4032,
      "height": 3024
    },
    {
      "src": "/photos/bramhatal/bramhatal-trek-garhwal-himalayas.jpg",
      "alt": "Snow-covered Himalayan peaks against a blue sky",
      "width": 4032,
      "height": 3024,
      "caption": "Day 3 — Summit Day"
    },
    {
      "src": "/photos/bramhatal/IMG_0446-scaled.jpg",
      "alt": "Sunrise on the peaks above Bramhatal base camp",
      "width": 4032,
      "height": 3024
    },
    {
      "src": "/photos/bramhatal/IMG_0449-scaled.jpg",
      "alt": "Final approach through knee-deep snow to the lake",
      "width": 4032,
      "height": 3024
    },
    {
      "src": "/photos/bramhatal/IMG_04491-scaled.jpg",
      "alt": "Looking back at the climb from the lake approach",
      "width": 4032,
      "height": 3024
    },
    {
      "src": "/photos/bramhatal/IMG_0450-scaled.jpg",
      "alt": "Bramhatal Lake completely frozen at 12,250 feet",
      "width": 4032,
      "height": 3024,
      "caption": "Bramhatal Lake at 3,592m"
    },
    {
      "src": "/photos/bramhatal/IMG_0452-scaled.jpg",
      "alt": "Standing at the edge of the frozen alpine lake",
      "width": 4032,
      "height": 3024
    },
    {
      "src": "/photos/bramhatal/IMG_0454-scaled.jpg",
      "alt": "Panoramic view of Bramhatal lake with surrounding peaks",
      "width": 4032,
      "height": 3024
    },
    {
      "src": "/photos/bramhatal/IMG_0471-scaled.jpg",
      "alt": "Descending from the lake in afternoon light",
      "width": 4032,
      "height": 3024
    },
    {
      "src": "/photos/bramhatal/IMG_0483-scaled.jpg",
      "alt": "Mt Trishul towering over the snowfield",
      "width": 4032,
      "height": 3024,
      "caption": "Mt Trishul (7,120m)"
    },
    {
      "src": "/photos/bramhatal/IMG_0488-scaled.jpg",
      "alt": "Last views of the Garhwal peaks before descending",
      "width": 4032,
      "height": 3024
    }
  ]
}
